request_rule_decorators/__init__.py
request_rule_decorators/decorator.py
request_rule_decorators/dto.py
request_rule_decorators/exceptions.py
request_rule_decorators/rules.py
request_rule_decorators/parsers/__init__.py
request_rule_decorators/parsers/base.py
request_rule_decorators/parsers/html_parser.py
request_rule_decorators/parsers/json_parser.py
request_rule_decorators/validators/__init__.py
request_rule_decorators/validators/base.py
request_rule_decorators/validators/blacklist_whitelist.py
request_rule_decorators/validators/content_type_validator.py
request_rule_decorators/validators/headers_validator.py
request_rule_decorators/validators/html_validator.py
request_rule_decorators/validators/json_validator.py
request_rule_decorators/validators/status_code_validator.py
request_rule_decorators-0.1.2.dist-info/licenses/LICENSE
request_rule_decorators-0.1.2.dist-info/METADATA
request_rule_decorators-0.1.2.dist-info/WHEEL
request_rule_decorators-0.1.2.dist-info/top_level.txt
request_rule_decorators-0.1.2.dist-info/RECORD
