Metadata-Version: 2.4
Name: request-rule-decorators
Version: 0.1.2
Summary: Library for validating and parsing HTTP response objects with decorators
Author-email: Your Name <your.email@example.com>
License: MIT
Project-URL: Homepage, https://github.com/yourusername/request-rule-decorators
Project-URL: Documentation, https://github.com/yourusername/request-rule-decorators/blob/main/DOCS.md
Project-URL: Repository, https://github.com/yourusername/request-rule-decorators
Project-URL: Issues, https://github.com/yourusername/request-rule-decorators/issues
Keywords: http,validation,parsing,decorator,response,json,html
Classifier: Development Status :: 4 - Beta
Classifier: Intended Audience :: Developers
Classifier: License :: OSI Approved :: MIT License
Classifier: Programming Language :: Python :: 3
Classifier: Programming Language :: Python :: 3.13
Classifier: Topic :: Software Development :: Libraries :: Python Modules
Classifier: Topic :: Internet :: WWW/HTTP
Requires-Python: >=3.13
License-File: LICENSE
Requires-Dist: httpx>=0.28.1
Requires-Dist: jsonpath-ng>=1.6.0
Requires-Dist: loguru>=0.7.3
Requires-Dist: lxml>=4.9.0
Provides-Extra: dev
Requires-Dist: pytest>=7.0.0; extra == "dev"
Requires-Dist: httpx>=0.24.0; extra == "dev"
Dynamic: license-file
